file_type/__init__.py
file_type/__init__.pyi
file_type/file_type.cp38-win_amd64.pyd
file_type/py.typed
filetype_py-1.0.0.dist-info/METADATA
filetype_py-1.0.0.dist-info/WHEEL
filetype_py-1.0.0.dist-info/RECORD
