Metadata-Version: 2.4
Name: filetype-py
Version: 1.0.0
Classifier: Programming Language :: Rust
Classifier: Programming Language :: Python :: Implementation :: CPython
Classifier: Programming Language :: Python :: Implementation :: PyPy
Summary: Python package for getting identifying file types, based on Rust's file_type crate.
Requires-Python: >=3.8
Project-URL: Repository, https://github.com/IoIxD/filetype_py
